[{"order_id": 9382, "coffee": "Americano", "size": "Small", "add_ons": [], "price": 5.0, "time": "2024-11-14 20:31:39", "est_pickup_time": "20:36:39", "payment_time": "2024-11-14 20:31:41"}, {"order_id": 1205, "coffee": "Cappuccino", "size": "Medium", "add_ons": [], "price": 6.5, "time": "2024-11-14 20:31:47", "est_pickup_time": "20:36:47", "payment_time": "2024-11-14 20:31:48"}, {"order_id": 3410, "coffee": "Caramel Macchiato", "size": "Small", "add_ons": [], "price": 7.0, "time": "2024-11-14 20:33:55", "est_pickup_time": "20:38:55"}, {"order_id": 4719, "coffee": "Americano", "size": "Large", "add_ons": [], "price": 5.0, "time": "2024-11-14 22:49:59", "est_pickup_time": "22:54:59"}, {"order_id": 9871, "coffee": "Americano", "size": "Small", "add_ons": [], "price": 5.0, "time": "2024-11-14 22:50:05", "est_pickup_time": "22:55:05"}, {"order_id": 5814, "coffee": "Americano", "size": "Large", "add_ons": [], "price": 5.0, "time": "2024-11-14 22:50:32", "est_pickup_time": "22:55:32", "payment_time": "2024-11-14 22:50:34"}, {"order_id": 8946, "coffee": "Americano", "size": "Medium", "add_ons": [], "price": 5.0, "time": "2024-11-14 22:50:39", "est_pickup_time": "22:55:39", "payment_time": "2024-11-14 22:50:40"}, {"order_id": 7625, "coffee": "Latte", "size": "Small", "add_ons": [], "price": 6.0, "time": "2024-11-14 22:50:44", "est_pickup_time": "22:55:44"}, {"order_id": 4691, "coffee": "Americano", "size": "Large", "add_ons": [], "price": 5.0, "time": "2024-11-14 22:56:07", "est_pickup_time": "23:01:07", "payment_time": "2024-11-14 22:56:09"}, {"order_id": 2166, "coffee": "Americano", "size": "Medium", "add_ons": [], "price": 5.0, "time": "2024-11-14 22:56:31", "est_pickup_time": "23:01:31"}, {"order_id": 9013, "coffee": "Cappuccino", "size": "Small", "add_ons": [], "price": 6.5, "time": "2024-11-14 22:56:34", "est_pickup_time": "23:01:34", "payment_time": "2024-11-14 22:56:36"}, {"order_id": 1497, "coffee": "Caramel Macchiato", "size": "Medium", "add_ons": [], "price": 7.0, "time": "2024-11-14 22:57:51", "est_pickup_time": "23:02:51", "payment_time": "2024-11-14 22:58:00"}, {"order_id": 4516, "coffee": "Latte", "size": "Medium", "add_ons": [], "price": 6.0, "time": "2024-11-14 22:59:08", "est_pickup_time": "23:04:08"}, {"order_id": 3114, "coffee": "Americano", "size": "Small", "add_ons": [], "price": 5.0, "time": "2024-11-14 23:02:25", "est_pickup_time": "23:07:25"}, {"order_id": 1083, "coffee": "Americano", "add_ons": [], "price": 5.0, "time": "2024-11-14 23:13:13", "est_pickup_time": "23:18:13"}, {"order_id": 4046, "coffee": "Americano", "size": "Medium", "add_ons": [], "price": 5.0, "time": "2024-11-14 23:17:47", "est_pickup_time": "23:22:47"}, {"order_id": 8329, "coffee": "Americano", "size": "Medium", "add_ons": [], "price": 4.5, "time": "2024-11-14 23:24:42", "est_pickup_time": "23:29:42", "payment_time": "2024-11-14 23:24:49"}, {"order_id": 6057, "coffee": "Caramel Macchiato", "size": "Small", "add_ons": [], "price": 6.3, "time": "2024-11-14 23:27:25", "est_pickup_time": "23:32:25"}, {"order_id": 9140, "coffee": "Americano", "size": "Medium", "add_ons": [], "price": 5.4, "time": "2024-11-14 23:43:29", "est_pickup_time": "23:48:29"}, {"order_id": 1174, "coffee": "Americano", "size": "Small", "add_ons": ["Milk"], "price": 6.3, "time": "2024-11-14 23:47:29", "est_pickup_time": "23:52:29"}, {"order_id": 2617, "coffee": "Americano", "size": "Large", "add_ons": ["Milk"], "price": 8.1, "time": "2024-11-14 23:54:37", "est_pickup_time": "23:59:37"}, {"order_id": 2186, "coffee": "Americano", "size": "Large", "add_ons": ["Milk"], "price": 8.1, "time": "2024-11-15 00:13:13", "est_pickup_time": "00:18:13"}, {"order_id": 1445, "coffee": "Caramel Macchiato", "size": "Large", "add_ons": ["Milk"], "price": 9.9, "time": "2024-11-15 00:17:49", "est_pickup_time": "00:22:49"}, {"order_id": 5968, "coffee": "Latte", "size": "Large", "add_ons": ["Extra Sugar"], "price": 8.1, "time": "2024-11-15 00:22:50", "est_pickup_time": "00:27:50"}, {"order_id": 4820, "coffee": "Latte", "size": "Large", "add_ons": ["Extra Sugar"], "price": 8.1, "time": "2024-11-15 00:44:58", "est_pickup_time": "00:49:58"}]